kt_ai_commons/__init__.py
kt_ai_commons/dataset.py
kt_ai_commons/featureCalculation.py
kt_ai_commons-1.2.1.dist-info/LICENSE
kt_ai_commons-1.2.1.dist-info/METADATA
kt_ai_commons-1.2.1.dist-info/WHEEL
kt_ai_commons-1.2.1.dist-info/top_level.txt
kt_ai_commons-1.2.1.dist-info/RECORD
