Metadata-Version: 2.1
Name: kt-ai-commons
Version: 1.2.1
Summary: module for artificial intelligence
Home-page: https://github.com/hodragon5237/kt_ai_commons
Author: hodragon
Author-email: giddens5237@gmail.com
License: BEERWARE
Platform: UNKNOWN
Classifier: Programming Language :: Python :: 3
Classifier: Operating System :: OS Independent
Requires-Dist: pandas
